npu/__init__.py
npu/version.py
npu/core/DataLoader.py
npu/core/Dataset.py
npu/core/Model.py
npu/core/Task.py
npu/core/__init__.py
npu/core/common.py
npu/core/compile.py
npu/core/export.py
npu/core/predict.py
npu/core/pub_cred_key.pub
npu/core/train.py
npu/core/saving/__init__.py
npu/core/saving/saving.py
npu/core/web/__init__.py
npu/core/web/urls.py
npu/loss/__init__.py
npu/metrics/__init__.py
npu/nlp/__init__.py
npu/nlp/datasets.py
npu/nlp/models.py
npu/optim/__init__.py
npu/vision/__init__.py
npu/vision/datasets.py
npu/vision/models.py
neuro-0.4.dev4.dist-info/LICENSE
neuro-0.4.dev4.dist-info/METADATA
neuro-0.4.dev4.dist-info/WHEEL
neuro-0.4.dev4.dist-info/top_level.txt
neuro-0.4.dev4.dist-info/RECORD
